pygeosolve/__init__.py
pygeosolve/_version.py
pygeosolve/constraints.py
pygeosolve/geometry.py
pygeosolve/plot.py
pygeosolve/problem.py
pygeosolve/util.py
pygeosolve-0.7.0.dist-info/LICENSE
pygeosolve-0.7.0.dist-info/METADATA
pygeosolve-0.7.0.dist-info/WHEEL
pygeosolve-0.7.0.dist-info/top_level.txt
pygeosolve-0.7.0.dist-info/RECORD
