Metadata-Version: 2.1
Name: pygeosolve
Version: 0.7.0
Summary: Geometric constraint solver
Home-page: https://github.com/SeanDS/pygeosolve
Author: Sean Leavey
Author-email: pygeosolve@attackllama.com
License: GPL-3.0-or-later
Project-URL: Bug Tracker, https://github.com/SeanDS/pygeosolve/issues
Project-URL: Source Code, https://github.com/SeanDS/pygeosolve/
Project-URL: Documentation, https://seands.github.io/pygeosolve/
Platform: UNKNOWN
Classifier: Development Status :: 4 - Beta
Classifier: Intended Audience :: Science/Research
Classifier: License :: OSI Approved :: GNU General Public License v3 or later (GPLv3+)
Classifier: Natural Language :: English
Classifier: Operating System :: OS Independent
Classifier: Programming Language :: Python
Classifier: Programming Language :: Python :: 3
Classifier: Programming Language :: Python :: 3.8
Classifier: Programming Language :: Python :: 3.9
Classifier: Programming Language :: Python :: 3.10
Classifier: Topic :: Scientific/Engineering
Requires-Python: >=3.8
Provides-Extra: dev
License-File: LICENSE
